llmem/README.md
llmem/__init__.py
llmem/maketable.py
llmem-20240215.post2.dist-info/METADATA
llmem-20240215.post2.dist-info/WHEEL
llmem-20240215.post2.dist-info/licenses/LICENSE
llmem-20240215.post2.dist-info/RECORD
