Metadata-Version: 2.1
Name: llmem
Version: 20240215.post2
Summary: Read through cache for OpenAI's API.
Project-URL: Homepage, https://llmem.com
Project-URL: Repository, https://github.com/c0g/llmem.git
Project-URL: Issues, https://github.com/c0g/llmem/issues
Author-email: Tom Nickson <tom@llmem.com>
License: Copyright (C) 2024 by Tom Nickson <tom@llmem.com>
License-File: LICENSE
Requires-Python: >=3.8
Requires-Dist: aiohttp[speedups]
Requires-Dist: aiosqlite
Requires-Dist: markdown
Requires-Dist: pymdown-extensions
Requires-Dist: starlette
Requires-Dist: uvicorn
